{"id":10924021,"category":"FOR_SALE","link":"/na-sprzedaz/wroclaw-srodmiescie-mieszczanska-10924021","desc":"Na sprzedaż kawalerka z własnym ogrodem i tarasem w centrum miasta. Idealna lokalizacja dla osób ceniących sobie bliskość miasta i naturę.\n\r\n\n\r\n\nBEZ prowizji oraz podatku 2% PCC !\n\r\n\n\r\n\nATUTY:\n\r\n- Mieszkanie nad rzeką\r\n- W pobliżu parku\r\n- Prestiżowe wykończenie części wspólnych\r\n- Własny ogródek\r\n\n\r\n\nInwestycja zlokalizowana w obrębie Kępy Mieszczańskiej nad samą Odrą oraz oferująca mieszkania z widokiem na 4-hektarowy Park Mieszczański. \r\n\n\r\nNa sprzedaż są mieszkania o ponadstandardowej wysokości - 2,71 m - i metrażach od 25 do 92,3 m². Do lokali przynależą ogródki, zielone tarasy lub balkony. Drzwi balkonowe w pokojach dziennych posiadają tzw. słupek ruchomy, dzięki czemu zapewniają maksymalne doświetlenie pomieszczeń.  \r\n\n\r\nW inwestycji uwzględniono dwupoziomowy garaż podziemny, rowerownię, eleganckie lobby, reprezentacyjne klatki wejściowe z elementami zieleni oraz nastrojowymi pasami ledowymi, a także windy i wideodomofony. Dodatkowo do dyspozycji mieszkańców jest pomysłowo zaaranżowany dziedziniec z przejściem na bulwar miejski.\r\n\n\r\n\nZdjęcia przedstawione w ofercie są wizualizacjami.\n\r\n\n\r\n\nTo tylko jedno z wielu mieszkań tej inwestycji, które mamy w ofercie!\n\r\n\nZamiast przeglądać kolejne ogłoszenia, zadzwoń: 730-396-827 i zapytaj o szczegóły.\n\r\n\n\r\nMarcin Kumiszczo\r\nHome Estate Wrocław","address":{"city":"Wrocław","district":"Śródmieście"},"images":[{"id":91844948,"description":null,"isScheme":false},{"id":91844949,"description":null,"isScheme":false},{"id":91844950,"description":null,"isScheme":false},{"id":91844951,"description":null,"isScheme":false},{"id":91844952,"description":null,"isScheme":false},{"id":91844953,"description":null,"isScheme":false}],"tourLink":null,"videoLink":null,"price":530640,"priceForm2":13200,"area":40.2,"numOfRooms":1,"constructYear":2023,"details":{"Balkon":null,"Liczba_lazienek":1,"Ogrodek":true,"Wysokosc_apartamentu":271}}